biond/__init__.py
biond/client.py
biond/req_client.py
biond/processes/__init__.py
biond/processes/blast_process.py
biond/processes/clustal_process.py
biond/processes/mafft_process.py
biond/processes/mrbayes_process.py
biond/processes/paup_process.py
biond/processes/pda_process.py
biond/processes/data_selectors/__init__.py
biond/processes/data_selectors/alignment_selector.py
biond/processes/data_selectors/geolayer_selector.py
biond/processes/data_selectors/phylotree_selector.py
biond/processes/data_selectors/sequence_selector.py
biond/processes/resources/__init__.py
biond/processes/resources/cipres_resource.py
biond/processes/resources/slurm_resource.py
biond/processes/resources/ssh_resource.py
ngd_biond-0.3.dist-info/LICENSE
ngd_biond-0.3.dist-info/METADATA
ngd_biond-0.3.dist-info/WHEEL
ngd_biond-0.3.dist-info/top_level.txt
ngd_biond-0.3.dist-info/RECORD
