Metadata-Version: 2.1
Name: ngd-biond
Version: 0.3
Summary: Client to NGD backend
Home-page: https://github.com/nextgendem/bcs-bond
Author: Rafael Nebot, Daniel Reyes
Author-email: rnebot@itccanarias.org, dreyes@itccanarias.org
License: BSD3
Platform: UNKNOWN
Requires-Python: >=3.8
Requires-Dist: requests
Requires-Dist: pandas
Requires-Dist: marshmallow
Requires-Dist: urllib3
Requires-Dist: typing
